{
  "id": "2013020397",
  "sid": "2013",
  "t": "02",
  "gn": "0397",
  "utcStart": "2013-12-01 00:00:00+0000",
  "easternStart": "2013-11-30 19:00:00",
  "summary": "Capitals send Islanders to sixth straight loss",
  "h": {
    "ab": "NYI",
    "record": "8-15-4",
    "live": "",
    "replayShort": "150",
    "replayShortNumber": 1,
    "replayFull": "150",
    "replayFullNumber": 1
  },
  "a": {
    "ab": "WSH",
    "record": "14-11-2",
    "live": "",
    "replayShort": "150",
    "replayShortNumber": 1,
    "replayFull": "150",
    "replayFullNumber": 1
  },
  "pbp": [
    {
      "key": "NYI385",
      "summary": "Aaron Volpatti (2) Wrist Shot, assists: Tom Wilson (3), Martin Erat (7)",
      "homeType": "goal",
      "homeNumber": 1,
      "awayType": "goal",
      "awayNumber": 1
    },
    {
      "key": "NYI112",
      "summary": "Pierre-Marc Bouchard Slap Shot saved by Braden Holtby",
      "homeType": "save",
      "homeNumber": 1,
      "awayType": "save",
      "awayNumber": 1
    },
    {
      "key": "NYI711",
      "summary": "Nicklas Backstrom (6) Wrist Shot, assists: Jason Chimera (11), Karl Alzner (5)",
      "homeType": "goal",
      "homeNumber": 1,
      "awayType": "goal",
      "awayNumber": 1
    },
    {
      "key": "NYI113",
      "summary": "Colin McDonald Wrist Shot saved by Braden Holtby",
      "homeType": "save",
      "homeNumber": 1,
      "awayType": "save",
      "awayNumber": 1
    },
    {
      "key": "NYI708",
      "summary": "Thomas Vanek (8) Wrist Shot, assists: John Tavares (19), Kyle Okposo (17)",
      "homeType": "goal",
      "homeNumber": 1,
      "awayType": "goal",
      "awayNumber": 1
    },
    {
      "key": "NYI104",
      "summary": "Nate Schmidt Wrist Shot saved by Anders Nilsson",
      "homeType": "save",
      "homeNumber": 1,
      "awayType": "save",
      "awayNumber": 1
    },
    {
      "key": "NYI722",
      "summary": "Alex Ovechkin (21) Snap Shot, assists: Mikhail Grabovski (14), Nate Schmidt (4)",
      "homeType": "goal",
      "homeNumber": 1,
      "awayType": "goal",
      "awayNumber": 1
    },
    {
      "key": "NYI108",
      "summary": "Colin McDonald Wrist Shot saved by Braden Holtby",
      "homeType": "save",
      "homeNumber": 1,
      "awayType": "save",
      "awayNumber": 1
    },
    {
      "key": "NYI477",
      "summary": "Cal Clutterbuck (3) Wrist Shot, assists: Andrew MacDonald (7), Casey Cizikas (4)",
      "homeType": "goal",
      "homeNumber": 1,
      "awayType": "goal",
      "awayNumber": 1
    }
  ]
}