{
  "id": "2013020453",
  "sid": "2013",
  "t": "02",
  "gn": "0453",
  "utcStart": "2013-12-09 01:00:00+0000",
  "easternStart": "2013-12-08 20:00:00",
  "summary": "Canucks continue homestand against Avalanche",
  "h": {
    "ab": "VAN",
    "record": "16-10-5",
    "live": "",
    "replayShort": "",
    "replayShortNumber": 0,
    "replayFull": "",
    "replayFullNumber": 0
  },
  "a": {
    "ab": "COL",
    "record": "20-7-0",
    "live": "",
    "replayShort": "",
    "replayShortNumber": 0,
    "replayFull": "",
    "replayFullNumber": 0
  },
  "pbp": []
}