{
  "id": "2013020122",
  "sid": "2013",
  "t": "02",
  "gn": "0122",
  "utcStart": "2013-10-20 02:30:00+0000",
  "easternStart": "2013-10-19 22:30:00",
  "summary": "",
  "h": {
    "ab": "LAK",
    "record": "4-3-0",
    "live": "",
    "replayShort": "",
    "replayShortNumber": 0,
    "replayFull": "",
    "replayFullNumber": 0
  },
  "a": {
    "ab": "DAL",
    "record": "2-3-0",
    "live": "",
    "replayShort": "",
    "replayShortNumber": 0,
    "replayFull": "",
    "replayFullNumber": 0
  },
  "pbp": []
}